{"version":"TaskSource_v1.0.0","name":"mission_root","groups":[{"name":"default","list":[{"key":"ButtonEventIn","guid":"A586C2F95B34133B","pos":{"x":9.0,"y":10.5},"links":[{"ipin":"Out","oguid":"37C39EA4BEB9BFDE","opin":"In"}],"fields":[{"key":"eventName","type":9,"value":"CLOSE"}]},{"key":"PopView","guid":"37C39EA4BEB9BFDE","pos":{"x":197.0,"y":11.5},"links":[],"fields":[{"key":"viewLayer","type":9,"value":"NONE"},{"key":"viewName","type":9,"value":""}]},{"key":"ButtonEventIn","guid":"DEFD579243D64A8","pos":{"x":26.67340087890625,"y":1077.0048828125},"links":[{"ipin":"Out","oguid":"246EC6484A1AAC2E","opin":"In"}],"fields":[{"key":"eventName","type":9,"value":"COMPLETE"}]},{"key":"Comment","guid":"FBD4199C1BE43A6","pos":{"x":26.67340087890625,"y":1037.005126953125},"links":[],"fields":[{"key":"color","type":13,"value":"RGBA(1.000, 1.000, 1.000, 1.000)"},{"key":"comment","type":9,"value":"達成済み"}]},{"key":"Comment","guid":"249BB0139A288EED","pos":{"x":34.949920654296878,"y":896.015380859375},"links":[],"fields":[{"key":"color","type":13,"value":"RGBA(1.000, 1.000, 1.000, 1.000)"},{"key":"comment","type":9,"value":"ヘルプ"}]},{"key":"Comment","guid":"D344F7D8F4C68C","pos":{"x":-0.28570556640625,"y":-43.58966064453125},"links":[],"fields":[{"key":"color","type":13,"value":"RGBA(1.000, 0.000, 0.000, 1.000)"},{"key":"comment","type":9,"value":"※各タブ制御は別グループ"}]},{"key":"ButtonEventIn","guid":"4E13A467572FEE80","pos":{"x":55.537811279296878,"y":1425.66357421875},"links":[{"ipin":"Out","oguid":"9D2843E515ED2A8","opin":"Bind"}],"fields":[{"key":"eventName","type":9,"value":"BULK_GET"}]},{"key":"Comment","guid":"F4BBDA84C6E6B88","pos":{"x":55.537811279296878,"y":1384.663330078125},"links":[],"fields":[{"key":"color","type":13,"value":"RGBA(1.000, 1.000, 1.000, 1.000)"},{"key":"comment","type":9,"value":"一括受取"}]},{"key":"ButtonEventIn","guid":"8B5AF88E1D76C18F","pos":{"x":24.4967041015625,"y":671.6964111328125},"links":[{"ipin":"Out","oguid":"52F431807A15F38","opin":"receive"}],"fields":[{"key":"eventName","type":9,"value":"TRY"}]},{"key":"Comment","guid":"412B194432CCF4E","pos":{"x":20.15740966796875,"y":631.508056640625},"links":[],"fields":[{"key":"color","type":13,"value":"RGBA(1.000, 1.000, 1.000, 1.000)"},{"key":"comment","type":9,"value":"挑戦する"}]},{"key":"ButtonEventIn","guid":"37428F191E51387","pos":{"x":53.744415283203128,"y":1314.41015625},"links":[{"ipin":"Out","oguid":"2AC2AA66F61B536B","opin":"get"},{"ipin":"Out","oguid":"A2509D4FF4BAF25D","opin":"receive"}],"fields":[{"key":"eventName","type":9,"value":"GET"}]},{"key":"Comment","guid":"6473CABB5F2146","pos":{"x":48.901153564453128,"y":1274.72607421875},"links":[],"fields":[{"key":"color","type":13,"value":"RGBA(1.000, 1.000, 1.000, 1.000)"},{"key":"comment","type":9,"value":"受け取る"}]},{"key":"ButtonEventIn","guid":"62498A53FFF6BF65","pos":{"x":28.05145263671875,"y":792.3189697265625},"links":[{"ipin":"Out","oguid":"AE79CACFAF944557","opin":"In"}],"fields":[{"key":"eventName","type":9,"value":"DETAIL"}]},{"key":"Comment","guid":"18512A45E7E77C48","pos":{"x":10.05029296875,"y":752.635009765625},"links":[],"fields":[{"key":"color","type":13,"value":"RGBA(1.000, 1.000, 1.000, 1.000)"},{"key":"comment","type":9,"value":"ミッション詳細"}]},{"key":"PushView","guid":"AE79CACFAF944557","pos":{"x":306.9163818359375,"y":780.0401611328125},"links":[],"fields":[{"key":"viewLayer","type":9,"value":"GLOBALMENU"},{"key":"viewName","type":9,"value":"MISSION_DETAIL"},{"key":"loadMode","type":14,"value":"0"},{"key":"isNotOpen","type":2,"value":"False"}]},{"key":"PushView","guid":"246EC6484A1AAC2E","pos":{"x":206.533935546875,"y":1077.564453125},"links":[],"fields":[{"key":"viewLayer","type":9,"value":"GLOBALMENU"},{"key":"viewName","type":9,"value":"MISSION_COMPLETELIST"},{"key":"loadMode","type":14,"value":"0"},{"key":"isNotOpen","type":2,"value":"False"}]},{"key":"Bind","guid":"837D18A167C599","pos":{"x":156.82095336914063,"y":668.322998046875},"links":[],"fields":[{"key":"SerializeData","type":1000,"value":"{\"type\":3,\"target\":\"\",\"values\":[{\"skey\":\"root\",\"dkey\":\"_data\",\"starget\":\"\",\"sfield\":\"\",\"type\":11,\"src\":1,\"dst\":1}]}"}]},{"key":"Bind","guid":"F13AA4FC3D82CF50","pos":{"x":170.06735229492188,"y":795.7862548828125},"links":[],"fields":[{"key":"SerializeData","type":1000,"value":"{\"type\":0,\"target\":\"\",\"values\":[{\"skey\":\"root\",\"dkey\":\"_data\",\"starget\":\"\",\"sfield\":\"\",\"type\":11,\"src\":1,\"dst\":1}]}"}]},{"key":"View","guid":"87D82C6F1618F780","pos":{"x":498.21533203125,"y":336.9754333496094},"links":[],"fields":[]},{"key":"Bind","guid":"C1CCC2B18393D183","pos":{"x":193.32467651367188,"y":1311.5108642578125},"links":[],"fields":[{"key":"SerializeData","type":1000,"value":"{\"type\":3,\"target\":\"\",\"values\":[{\"skey\":\"root\",\"dkey\":\"_data\",\"starget\":\"\",\"sfield\":\"\",\"type\":11,\"src\":1,\"dst\":1}]}"}]},{"key":"HomeRequestMoveMission","guid":"928550FD407C9352","pos":{"x":495.7613525390625,"y":702.1097412109375},"links":[],"fields":[]},{"key":"SystemEventIn","guid":"41B68C739E986B91","pos":{"x":30.998870849609376,"y":-221.52859497070313},"links":[{"ipin":"Out","oguid":"B79A021AB3824A6","opin":"mission/get"}],"fields":[{"key":"eventType","type":14,"value":"1"}]},{"key":"SystemEventOut","guid":"1D8FF0FAE1CAA4D8","pos":{"x":559.9988403320313,"y":-222.52859497070313},"links":[],"fields":[{"key":"eventType","type":14,"value":"2"}]},{"key":"TargetWebAPI","guid":"B79A021AB3824A6","pos":{"x":233.99887084960938,"y":-229.52859497070313},"links":[{"ipin":"Success","oguid":"E9ECAE1696552930","opin":"missionpack_info"}],"fields":[{"key":"Target","type":9,"value":"root"}]},{"key":"TargetWebAPI","guid":"BAF73C23C7B8FD4","pos":{"x":999.0436401367188,"y":1381.68603515625},"links":[{"ipin":"Success","oguid":"6729AD2B1FF6F596","opin":"In"}],"fields":[{"key":"Target","type":9,"value":"root"}]},{"key":"Comment","guid":"1E96491748959AFE","pos":{"x":995.6347045898438,"y":1333.958984375},"links":[],"fields":[{"key":"color","type":13,"value":"RGBA(1.000, 1.000, 1.000, 1.000)"},{"key":"comment","type":9,"value":"通信処理"}]},{"key":"PushView","guid":"6729AD2B1FF6F596","pos":{"x":1156.5770263671875,"y":1268.0491943359375},"links":[{"ipin":"Closed","oguid":"D3BFEFCBD17B0F2","opin":"If"},{"ipin":"Opened","oguid":"ADBB24AEC42BC2E2","opin":"In"}],"fields":[{"key":"viewLayer","type":9,"value":"GLOBALMENU"},{"key":"viewName","type":9,"value":"MISSION_REWARD"},{"key":"loadMode","type":14,"value":"0"},{"key":"isNotOpen","type":2,"value":"False"}]},{"key":"ButtonEventIn","guid":"7A6B32219B6F5A6","pos":{"x":84.88288879394531,"y":1837.041259765625},"links":[{"ipin":"Out","oguid":"5F596A62CDDD1D1","opin":"Bind"}],"fields":[{"key":"eventName","type":9,"value":"REWARD_GET"}]},{"key":"Comment","guid":"E2EB373B9D6316EC","pos":{"x":70.88282775878906,"y":1795.041259765625},"links":[],"fields":[{"key":"color","type":13,"value":"RGBA(1.000, 1.000, 1.000, 1.000)"},{"key":"comment","type":9,"value":"進捗報酬獲得"}]},{"key":"Bind","guid":"5F596A62CDDD1D1","pos":{"x":218.67872619628907,"y":1838.553466796875},"links":[{"ipin":"Out","oguid":"B57B11EAFE45A8AF","opin":"progReceive"}],"fields":[{"key":"SerializeData","type":1000,"value":"{\"type\":3,\"target\":\"\",\"values\":[{\"skey\":\"root\",\"dkey\":\"_data\",\"starget\":\"\",\"sfield\":\"\",\"type\":11,\"src\":1,\"dst\":1}]}"}]},{"key":"MissionCheckAp","guid":"35B2CCE1C64BCF77","pos":{"x":584.2060546875,"y":1374.33447265625},"links":[{"ipin":"noReceive","oguid":"5244284F171E1AB5","opin":"Open"},{"ipin":"checkReceive","oguid":"AD198D5167E982EF","opin":"Open"},{"ipin":"direct","oguid":"BAF73C23C7B8FD4","opin":"mission/reward"}],"fields":[]},{"key":"DialogOneButton","guid":"5244284F171E1AB5","pos":{"x":803.9008178710938,"y":1270.861328125},"links":[],"fields":[{"key":"button_ok","type":9,"value":""},{"key":"_sys_dialog","type":2,"value":"False"},{"key":"_title","type":9,"value":"Sys.REWARD_RECEIVE"},{"key":"_msg","type":9,"value":"Sys.AP_NOT_RECEIVE_FOR_UPPER"},{"key":"_bgTapClose","type":2,"value":"True"},{"key":"_button_ignoreLock","type":2,"value":"True"},{"key":"_auto_release","type":2,"value":"False"}]},{"key":"DialogTwoButton","guid":"AD198D5167E982EF","pos":{"x":810.9912719726563,"y":1377.22509765625},"links":[{"ipin":"YES","oguid":"BAF73C23C7B8FD4","opin":"mission/reward"}],"fields":[{"key":"button_yes","type":9,"value":""},{"key":"button_no","type":9,"value":""},{"key":"_sys_dialog","type":2,"value":"False"},{"key":"_title","type":9,"value":"Sys.REWARD_RECEIVE"},{"key":"_msg","type":9,"value":"Sys.AP_REMOVE_FOR_OVER"},{"key":"_bgTapClose","type":2,"value":"True"},{"key":"_button_ignoreLock","type":2,"value":"True"},{"key":"_auto_release","type":2,"value":"False"}]},{"key":"TargetWebAPI","guid":"ADA028CCD694843D","pos":{"x":1099.29541015625,"y":1850.81689453125},"links":[{"ipin":"Success","oguid":"662AE6E077BFC64D","opin":"In"}],"fields":[{"key":"Target","type":9,"value":"root"}]},{"key":"Comment","guid":"476A66AC1BD48AE1","pos":{"x":1095.886474609375,"y":1803.0894775390625},"links":[],"fields":[{"key":"color","type":13,"value":"RGBA(1.000, 1.000, 1.000, 1.000)"},{"key":"comment","type":9,"value":"通信処理"}]},{"key":"PushView","guid":"662AE6E077BFC64D","pos":{"x":1275.020263671875,"y":1769.2122802734375},"links":[{"ipin":"Closed","oguid":"5DFD3C7617B6C4E","opin":"If"},{"ipin":"Opened","oguid":"A4241E217B6610F7","opin":"In"}],"fields":[{"key":"viewLayer","type":9,"value":"GLOBALMENU"},{"key":"viewName","type":9,"value":"MISSION_REWARD"},{"key":"loadMode","type":14,"value":"0"},{"key":"isNotOpen","type":2,"value":"False"}]},{"key":"MissionCheckAp","guid":"DB4693CCBB684AB","pos":{"x":667.4365234375,"y":1790.2728271484375},"links":[{"ipin":"direct","oguid":"ADA028CCD694843D","opin":"mission/progreward"},{"ipin":"noReceive","oguid":"2CF727FDB3E4B7","opin":"Open"},{"ipin":"checkReceive","oguid":"8CC9D848FA48E29","opin":"Open"}],"fields":[]},{"key":"Bind","guid":"9D2843E515ED2A8","pos":{"x":193.19155883789063,"y":1439.3326416015625},"links":[{"ipin":"Out","oguid":"35B2CCE1C64BCF77","opin":"bulkReceive"}],"fields":[{"key":"SerializeData","type":1000,"value":"{\"type\":3,\"target\":\"\",\"values\":[{\"skey\":\"selectGrp\",\"dkey\":\"_grpData\",\"starget\":\"\",\"sfield\":\"\",\"type\":1,\"src\":0,\"dst\":0}]}"}]},{"key":"LocalEventOut","guid":"C68DFF0E7C06D5","pos":{"x":1880.4779052734375,"y":1528.08984375},"links":[],"fields":[{"key":"eventName","type":9,"value":"UPDATE_MISSION"}]},{"key":"LocalEventOut","guid":"46193EC33B9C1A2A","pos":{"x":1821.064208984375,"y":1960.8248291015625},"links":[],"fields":[{"key":"eventName","type":9,"value":"UPDATE_PROGRESS"}]},{"key":"LocalEventIn","guid":"D17A7AC13F4B553D","pos":{"x":297.0989990234375,"y":459.89447021484377},"links":[{"ipin":"Out","oguid":"87D82C6F1618F780","opin":"updateList"}],"fields":[{"key":"eventName","type":9,"value":"UPDATE_MISSION"}]},{"key":"LocalEventIn","guid":"E1AB6EAA5F459B50","pos":{"x":282.8133544921875,"y":535.0372924804688},"links":[{"ipin":"Out","oguid":"87D82C6F1618F780","opin":"updateProg"},{"ipin":"Out","oguid":"87D82C6F1618F780","opin":"updateBadge"}],"fields":[{"key":"eventName","type":9,"value":"UPDATE_PROGRESS"}]},{"key":"PushTextEffectView","guid":"6DE587EB7BF3FE8","pos":{"x":1479.7073974609375,"y":1308.37548828125},"links":[{"ipin":"Closed","oguid":"74F144DDD2B25EFA","opin":"In"}],"fields":[{"key":"viewLayer","type":9,"value":"GLOBALMENU"},{"key":"TextEffectType","type":9,"value":"PlayerRankUp"}]},{"key":"PushTextEffectView","guid":"E4A488C4DE696EEF","pos":{"x":1605.151611328125,"y":1840.0662841796875},"links":[{"ipin":"Closed","oguid":"46193EC33B9C1A2A","opin":"In"}],"fields":[{"key":"viewLayer","type":9,"value":"GLOBALMENU"},{"key":"TextEffectType","type":9,"value":"PlayerRankUp"}]},{"key":"HomeCheckPlayerRankup","guid":"D3BFEFCBD17B0F2","pos":{"x":1307.8358154296875,"y":1343.180908203125},"links":[{"ipin":"True","oguid":"6DE587EB7BF3FE8","opin":"In"},{"ipin":"False","oguid":"74F144DDD2B25EFA","opin":"In"}],"fields":[]},{"key":"HomeCheckPlayerRankup","guid":"5DFD3C7617B6C4E","pos":{"x":1434.503173828125,"y":1879.2481689453125},"links":[{"ipin":"True","oguid":"E4A488C4DE696EEF","opin":"In"},{"ipin":"False","oguid":"46193EC33B9C1A2A","opin":"In"}],"fields":[]},{"key":"DialogOneButton","guid":"2CF727FDB3E4B7","pos":{"x":888.219482421875,"y":1680.5379638671875},"links":[],"fields":[{"key":"button_ok","type":9,"value":""},{"key":"_sys_dialog","type":2,"value":"False"},{"key":"_title","type":9,"value":"Sys.REWARD_RECEIVE"},{"key":"_msg","type":9,"value":"Sys.AP_NOT_RECEIVE_FOR_UPPER"},{"key":"_bgTapClose","type":2,"value":"True"},{"key":"_button_ignoreLock","type":2,"value":"True"},{"key":"_auto_release","type":2,"value":"False"}]},{"key":"DialogTwoButton","guid":"8CC9D848FA48E29","pos":{"x":892.1671142578125,"y":1788.4327392578125},"links":[{"ipin":"YES","oguid":"ADA028CCD694843D","opin":"mission/progreward"}],"fields":[{"key":"button_yes","type":9,"value":""},{"key":"button_no","type":9,"value":""},{"key":"_sys_dialog","type":2,"value":"False"},{"key":"_title","type":9,"value":"Sys.REWARD_RECEIVE"},{"key":"_msg","type":9,"value":"Sys.AP_REMOVE_FOR_OVER"},{"key":"_bgTapClose","type":2,"value":"True"},{"key":"_button_ignoreLock","type":2,"value":"True"},{"key":"_auto_release","type":2,"value":"False"}]},{"key":"ButtonEventIn","guid":"E5DF72902531374","pos":{"x":31.438232421875,"y":938.9930419921875},"links":[{"ipin":"Out","oguid":"5D9DD0E6545FA5C","opin":"In"}],"fields":[{"key":"eventName","type":9,"value":"HELP"}]},{"key":"Comment","guid":"3B904AB1DE14A0D7","pos":{"x":1475.4088134765625,"y":1121.5064697265625},"links":[],"fields":[{"key":"color","type":13,"value":"RGBA(1.000, 1.000, 1.000, 1.000)"},{"key":"comment","type":9,"value":"所持数超過表示"}]},{"key":"GainDircPushView","guid":"ADBB24AEC42BC2E2","pos":{"x":1310.912353515625,"y":1167.2371826171875},"links":[{"ipin":"Closed","oguid":"B248E4172B24EE92","opin":"In"},{"ipin":"None","oguid":"B248E4172B24EE92","opin":"In"}],"fields":[{"key":"viewLayer","type":9,"value":"GLOBALMENU"},{"key":"loadMode","type":14,"value":"0"}]},{"key":"CapOverPushView","guid":"B248E4172B24EE92","pos":{"x":1484.682373046875,"y":1156.7796630859375},"links":[],"fields":[{"key":"viewLayer","type":9,"value":"DEFAULT"},{"key":"loadMode","type":14,"value":"0"}]},{"key":"Comment","guid":"C1EB964D88C3316C","pos":{"x":1616.8709716796875,"y":1650.3946533203125},"links":[],"fields":[{"key":"color","type":13,"value":"RGBA(1.000, 1.000, 1.000, 1.000)"},{"key":"comment","type":9,"value":"所持数超過表示"}]},{"key":"GainDircPushView","guid":"A4241E217B6610F7","pos":{"x":1451.0587158203125,"y":1682.9674072265625},"links":[{"ipin":"Closed","oguid":"8CA7C88E526CEE7A","opin":"In"},{"ipin":"None","oguid":"8CA7C88E526CEE7A","opin":"In"}],"fields":[{"key":"viewLayer","type":9,"value":"GLOBALMENU"},{"key":"loadMode","type":14,"value":"0"}]},{"key":"CapOverPushView","guid":"8CA7C88E526CEE7A","pos":{"x":1626.1444091796875,"y":1685.6678466796875},"links":[],"fields":[{"key":"viewLayer","type":9,"value":"DEFAULT"},{"key":"loadMode","type":14,"value":"0"}]},{"key":"MissionCheckPeriod","guid":"52F431807A15F38","pos":{"x":311.38348388671877,"y":653.1224365234375},"links":[{"ipin":"False","oguid":"928550FD407C9352","opin":"In"},{"ipin":"True","oguid":"363BFA486CB56C59","opin":"Open"}],"fields":[]},{"key":"DialogOneButton","guid":"363BFA486CB56C59","pos":{"x":501.78399658203127,"y":602.6029052734375},"links":[],"fields":[{"key":"button_ok","type":9,"value":""},{"key":"_sys_dialog","type":2,"value":"False"},{"key":"_title","type":9,"value":"Sys.MISSION_TIMEOUT_TRY_TITLE"},{"key":"_msg","type":9,"value":"Sys.MISSION_TIMEOUT_TRY_DESC"},{"key":"_bgTapClose","type":2,"value":"True"},{"key":"_button_ignoreLock","type":2,"value":"True"},{"key":"_auto_release","type":2,"value":"False"}]},{"key":"MissionCheckPeriod","guid":"A2509D4FF4BAF25D","pos":{"x":364.99981689453127,"y":1317.6466064453125},"links":[{"ipin":"True","oguid":"2943EDE73E9E515","opin":"Open"},{"ipin":"False","oguid":"35B2CCE1C64BCF77","opin":"receive"}],"fields":[]},{"key":"DialogOneButton","guid":"2943EDE73E9E515","pos":{"x":530.9323120117188,"y":1237.339599609375},"links":[],"fields":[{"key":"button_ok","type":9,"value":""},{"key":"_sys_dialog","type":2,"value":"False"},{"key":"_title","type":9,"value":"Sys.MISSION_TIMEOUT_TITLE"},{"key":"_msg","type":9,"value":"Sys.MISSION_TIMEOUT_DESC"},{"key":"_bgTapClose","type":2,"value":"True"},{"key":"_button_ignoreLock","type":2,"value":"True"},{"key":"_auto_release","type":2,"value":"False"}]},{"key":"MissionCheckPeriod","guid":"B57B11EAFE45A8AF","pos":{"x":369.78009033203127,"y":1805.1395263671875},"links":[{"ipin":"True","oguid":"BC7CDA748220CD1","opin":"Open"},{"ipin":"False","oguid":"DB4693CCBB684AB","opin":"progReceive"}],"fields":[]},{"key":"DialogOneButton","guid":"BC7CDA748220CD1","pos":{"x":564.4663696289063,"y":1644.6201171875},"links":[],"fields":[{"key":"button_ok","type":9,"value":""},{"key":"_sys_dialog","type":2,"value":"False"},{"key":"_title","type":9,"value":"Sys.MISSION_TIMEOUT_TITLE"},{"key":"_msg","type":9,"value":"Sys.MISSION_TIMEOUT_DESC"},{"key":"_bgTapClose","type":2,"value":"True"},{"key":"_button_ignoreLock","type":2,"value":"True"},{"key":"_auto_release","type":2,"value":"False"}]},{"key":"Controller","guid":"2AC2AA66F61B536B","pos":{"x":373.66265869140627,"y":1118.96533203125},"links":[],"fields":[]},{"key":"TargetWebAPI","guid":"E9ECAE1696552930","pos":{"x":396.81939697265627,"y":-226.57623291015626},"links":[{"ipin":"Success","oguid":"1D8FF0FAE1CAA4D8","opin":"In"}],"fields":[{"key":"Target","type":9,"value":"root"}]},{"key":"Controller","guid":"D1AF5019AD77F39","pos":{"x":286.38958740234377,"y":2069.1435546875},"links":[],"fields":[]},{"key":"ViewEventIn","guid":"F95256598A8CC5C2","pos":{"x":74.95330810546875,"y":2154.373046875},"links":[{"ipin":"Out","oguid":"D1AF5019AD77F39","opin":"updateBadge"}],"fields":[{"key":"eventName","type":9,"value":"UPDATE_BADGE"}]},{"key":"Comment","guid":"5058F6426477ECAB","pos":{"x":109.34765625,"y":2040.81103515625},"links":[],"fields":[{"key":"color","type":13,"value":"RGBA(1.000, 1.000, 1.000, 1.000)"},{"key":"comment","type":9,"value":"バッジ更新"}]},{"key":"ButtonEventIn","guid":"6BE42CDA2368C23F","pos":{"x":30.292724609375,"y":240.8565673828125},"links":[{"ipin":"Out","oguid":"87D82C6F1618F780","opin":"prevType"}],"fields":[{"key":"eventName","type":9,"value":"PREV"}]},{"key":"ButtonEventIn","guid":"B88CE7ABAA7D49B","pos":{"x":29.292724609375,"y":328.8565673828125},"links":[{"ipin":"Out","oguid":"87D82C6F1618F780","opin":"nextType"}],"fields":[{"key":"eventName","type":9,"value":"NEXT"}]},{"key":"Comment","guid":"7B2642216B41FDAB","pos":{"x":22.292724609375,"y":200.8565673828125},"links":[],"fields":[{"key":"color","type":13,"value":"RGBA(1.000, 1.000, 1.000, 1.000)"},{"key":"comment","type":9,"value":"タイプ<<"}]},{"key":"Comment","guid":"E8BC74E038DE4336","pos":{"x":23.292724609375,"y":294.8565673828125},"links":[],"fields":[{"key":"color","type":13,"value":"RGBA(1.000, 1.000, 1.000, 1.000)"},{"key":"comment","type":9,"value":"タイプ>>"}]},{"key":"SystemEventIn","guid":"DD5E6E7DFB968641","pos":{"x":743.9481201171875,"y":-92.68887329101563},"links":[{"ipin":"Out","oguid":"AB995893F75F56C","opin":"In"}],"fields":[{"key":"eventType","type":14,"value":"6"}]},{"key":"ViewEventOut","guid":"AB995893F75F56C","pos":{"x":925.376953125,"y":-88.40312194824219},"links":[],"fields":[{"key":"viewName","type":9,"value":"HOME_ROOT"},{"key":"eventName","type":9,"value":"OPEN_VIPRANKUP"}]},{"key":"OpenWebHelpView","guid":"5D9DD0E6545FA5C","pos":{"x":227.28079223632813,"y":942.8656005859375},"links":[],"fields":[{"key":"openURL","type":9,"value":"mission"},{"key":"caption","type":9,"value":"Help.MISSION_TITLE"}]},{"key":"HasNewHotDealPending","guid":"42BDB09267291F7B","pos":{"x":1652.1207275390625,"y":1441.058349609375},"links":[{"ipin":"True","oguid":"3FD5344ECA263342","opin":"In"},{"ipin":"False","oguid":"C68DFF0E7C06D5","opin":"In"}],"fields":[]},{"key":"PushView","guid":"3FD5344ECA263342","pos":{"x":1835.9105224609375,"y":1367.99853515625},"links":[{"ipin":"Closed","oguid":"C68DFF0E7C06D5","opin":"In"}],"fields":[{"key":"viewLayer","type":9,"value":"GLOBALMENU"},{"key":"viewName","type":9,"value":"HOTDEAL_APPEAL"},{"key":"loadMode","type":14,"value":"0"},{"key":"isNotOpen","type":2,"value":"False"}]},{"key":"ConditionRegion","guid":"74F144DDD2B25EFA","pos":{"x":1503.6802978515625,"y":1475.88671875},"links":[{"ipin":"WW","oguid":"42BDB09267291F7B","opin":"In"},{"ipin":"JA","oguid":"C68DFF0E7C06D5","opin":"In"}],"fields":[]}]},{"name":"daily","list":[{"key":"ButtonEventIn","guid":"29607D99CF16F6D","pos":{"x":20.285552978515626,"y":57.14619445800781},"links":[{"ipin":"Out","oguid":"3FC1991725CAF246","opin":"dailySub"}],"fields":[{"key":"eventName","type":9,"value":"DAILY_REGULAR"}]},{"key":"Comment","guid":"EE9594E5521D7ADC","pos":{"x":17.2855224609375,"y":15.14617919921875},"links":[],"fields":[{"key":"color","type":13,"value":"RGBA(1.000, 1.000, 1.000, 1.000)"},{"key":"comment","type":9,"value":"レギュラー"}]},{"key":"ButtonEventIn","guid":"FE3CC24FBFB1EDDB","pos":{"x":23.285552978515626,"y":169.1461944580078},"links":[{"ipin":"Out","oguid":"3FC1991725CAF246","opin":"dailySub"}],"fields":[{"key":"eventName","type":9,"value":"DAILY_EVENT"}]},{"key":"Comment","guid":"F826CCD8A14EC86","pos":{"x":28.2855224609375,"y":130.14617919921876},"links":[],"fields":[{"key":"color","type":13,"value":"RGBA(1.000, 1.000, 1.000, 1.000)"},{"key":"comment","type":9,"value":"イベント"}]},{"key":"View","guid":"3FC1991725CAF246","pos":{"x":307.92169189453127,"y":43.606781005859378},"links":[],"fields":[]},{"key":"ButtonEventIn","guid":"895A87B538C6D9","pos":{"x":25.681671142578126,"y":599.8807983398438},"links":[{"ipin":"Out","oguid":"676523B62BB6D55","opin":"Bind"}],"fields":[{"key":"eventName","type":9,"value":"REWARD_DETAIL"}]},{"key":"Comment","guid":"A1F890C8123CD86","pos":{"x":18.681640625,"y":559.8807983398438},"links":[],"fields":[{"key":"color","type":13,"value":"RGBA(1.000, 1.000, 1.000, 1.000)"},{"key":"comment","type":9,"value":"進捗報酬一覧"}]},{"key":"PushView","guid":"7E13105517E928","pos":{"x":312.9971923828125,"y":602.3832397460938},"links":[],"fields":[{"key":"viewLayer","type":9,"value":"GLOBALMENU"},{"key":"viewName","type":9,"value":"MISSION_REWARD"},{"key":"loadMode","type":14,"value":"0"},{"key":"isNotOpen","type":2,"value":"False"}]},{"key":"ButtonEventIn","guid":"748D1D735D30608A","pos":{"x":25.5836181640625,"y":280.7552490234375},"links":[{"ipin":"Out","oguid":"3FC1991725CAF246","opin":"dailySub"}],"fields":[{"key":"eventName","type":9,"value":"DAILY_WEEKSTART"}]},{"key":"Comment","guid":"E7CCEE9AB4EFA955","pos":{"x":24.583587646484376,"y":240.75521850585938},"links":[],"fields":[{"key":"color","type":13,"value":"RGBA(1.000, 1.000, 1.000, 1.000)"},{"key":"comment","type":9,"value":"月曜ボーナス"}]},{"key":"ButtonEventIn","guid":"20A254E9AF048F4","pos":{"x":23.5836181640625,"y":393.7552490234375},"links":[{"ipin":"Out","oguid":"3FC1991725CAF246","opin":"dailySub"}],"fields":[{"key":"eventName","type":9,"value":"DAILY_COMBACK"}]},{"key":"Comment","guid":"FDA7ECCCCB5416EB","pos":{"x":23.583587646484376,"y":353.7552185058594},"links":[],"fields":[{"key":"color","type":13,"value":"RGBA(1.000, 1.000, 1.000, 1.000)"},{"key":"comment","type":9,"value":"カムバック"}]},{"key":"Bind","guid":"676523B62BB6D55","pos":{"x":177.24273681640626,"y":598.231689453125},"links":[{"ipin":"Out","oguid":"7E13105517E928","opin":"In"}],"fields":[{"key":"SerializeData","type":1000,"value":"{\"type\":3,\"target\":\"\",\"values\":[{\"skey\":\"root\",\"dkey\":\"request\",\"starget\":\"\",\"sfield\":\"\",\"type\":11,\"src\":1,\"dst\":1}]}"}]},{"key":"ButtonEventIn","guid":"76A61F6139EE2157","pos":{"x":227.50750732421876,"y":395.8890075683594},"links":[{"ipin":"Out","oguid":"3FC1991725CAF246","opin":"dailySub"}],"fields":[{"key":"eventName","type":9,"value":"WW_WEEKLY"}]}]},{"name":"record","list":[{"key":"Comment","guid":"71BAB6BCE52D72EF","pos":{"x":10.231689453125,"y":6.2046661376953129},"links":[],"fields":[{"key":"color","type":13,"value":"RGBA(1.000, 1.000, 1.000, 1.000)"},{"key":"comment","type":9,"value":"クエスト"}]},{"key":"ButtonEventIn","guid":"A6EB13528442A7DA","pos":{"x":9.1678466796875,"y":46.63020324707031},"links":[{"ipin":"Out","oguid":"CE2F4B8FDB4E1A1D","opin":"recordSub"}],"fields":[{"key":"eventName","type":9,"value":"RECORD_QUEST"}]},{"key":"Comment","guid":"F625DEC05959A38A","pos":{"x":12.359375,"y":114.71528625488281},"links":[],"fields":[{"key":"color","type":13,"value":"RGBA(1.000, 1.000, 1.000, 1.000)"},{"key":"comment","type":9,"value":"異界の城"}]},{"key":"ButtonEventIn","guid":"1D92B1CEDBDC278","pos":{"x":11.2955322265625,"y":155.1408233642578},"links":[{"ipin":"Out","oguid":"CE2F4B8FDB4E1A1D","opin":"recordSub"}],"fields":[{"key":"eventName","type":9,"value":"RECORD_LOBBY"}]},{"key":"Comment","guid":"734531DCCE9E9C2","pos":{"x":10.23175048828125,"y":218.9706573486328},"links":[],"fields":[{"key":"color","type":13,"value":"RGBA(1.000, 1.000, 1.000, 1.000)"},{"key":"comment","type":9,"value":"バトル"}]},{"key":"ButtonEventIn","guid":"B3B7C9448023A4D1","pos":{"x":9.16790771484375,"y":259.39617919921877},"links":[{"ipin":"Out","oguid":"CE2F4B8FDB4E1A1D","opin":"recordSub"}],"fields":[{"key":"eventName","type":9,"value":"RECORD_PVP"}]},{"key":"Comment","guid":"ADF6751BB39CCD","pos":{"x":12.35943603515625,"y":327.48126220703127},"links":[],"fields":[{"key":"color","type":13,"value":"RGBA(1.000, 1.000, 1.000, 1.000)"},{"key":"comment","type":9,"value":"イベント"}]},{"key":"ButtonEventIn","guid":"3B38D53C57B635B9","pos":{"x":11.29559326171875,"y":367.90679931640627},"links":[{"ipin":"Out","oguid":"CE2F4B8FDB4E1A1D","opin":"recordSub"}],"fields":[{"key":"eventName","type":9,"value":"RECORD_EVENT"}]},{"key":"Comment","guid":"622224EA899F745","pos":{"x":13.2955322265625,"y":436.92803955078127},"links":[],"fields":[{"key":"color","type":13,"value":"RGBA(1.000, 1.000, 1.000, 1.000)"},{"key":"comment","type":9,"value":"育成"}]},{"key":"ButtonEventIn","guid":"DD8CEF1A1931BA0","pos":{"x":10.231689453125,"y":475.35357666015627},"links":[{"ipin":"Out","oguid":"CE2F4B8FDB4E1A1D","opin":"recordSub"}],"fields":[{"key":"eventName","type":9,"value":"RECORD_GROWTH"}]},{"key":"Comment","guid":"73927E2F6AE150B1","pos":{"x":0.73486328125,"y":837.0823364257813},"links":[],"fields":[{"key":"color","type":13,"value":"RGBA(1.000, 1.000, 1.000, 1.000)"},{"key":"comment","type":9,"value":"マルチグループ選択"}]},{"key":"ButtonEventIn","guid":"70226890AC9CDC33","pos":{"x":17.6810302734375,"y":878.635498046875},"links":[{"ipin":"Out","oguid":"CE2F4B8FDB4E1A1D","opin":"selMultiGrp"}],"fields":[{"key":"eventName","type":9,"value":"SEL_MULTI_GRP"}]},{"key":"View","guid":"CE2F4B8FDB4E1A1D","pos":{"x":422.240234375,"y":541.6895751953125},"links":[],"fields":[]},{"key":"Comment","guid":"647A9EF44EF657C6","pos":{"x":11.12481689453125,"y":546.8565673828125},"links":[],"fields":[{"key":"color","type":13,"value":"RGBA(1.000, 1.000, 1.000, 1.000)"},{"key":"comment","type":9,"value":"カムバック"}]},{"key":"ButtonEventIn","guid":"C33420B742C9A2A8","pos":{"x":8.06097412109375,"y":585.2821044921875},"links":[{"ipin":"Out","oguid":"CE2F4B8FDB4E1A1D","opin":"recordSub"}],"fields":[{"key":"eventName","type":9,"value":"RECORD_COMEBACK"}]},{"key":"Comment","guid":"361815B70B4CCA9","pos":{"x":3.190765380859375,"y":656.613525390625},"links":[],"fields":[{"key":"color","type":13,"value":"RGBA(1.000, 1.000, 1.000, 1.000)"},{"key":"comment","type":9,"value":"イベントアーカイブ(書庫機能)"}]},{"key":"ButtonEventIn","guid":"8E3A8D7B3D7D4F55","pos":{"x":8.69842529296875,"y":693.6104736328125},"links":[{"ipin":"Out","oguid":"CE2F4B8FDB4E1A1D","opin":"recordSub"}],"fields":[{"key":"eventName","type":9,"value":"RECORD_ARCHIVE"}]}]},{"name":"pack","list":[{"key":"Comment","guid":"C25A48999BC58452","pos":{"x":23.430694580078126,"y":9.852462768554688},"links":[],"fields":[{"key":"color","type":13,"value":"RGBA(1.000, 1.000, 1.000, 1.000)"},{"key":"comment","type":9,"value":"クエスト"}]},{"key":"ButtonEventIn","guid":"27B3744C4864B8C1","pos":{"x":22.366851806640626,"y":50.27799987792969},"links":[{"ipin":"Out","oguid":"F0B52BA1B3A8BB26","opin":"packSub"}],"fields":[{"key":"eventName","type":9,"value":"PACK_QUEST"}]},{"key":"View","guid":"F0B52BA1B3A8BB26","pos":{"x":186.439208984375,"y":49.33738708496094},"links":[],"fields":[]}]},{"name":"ww","list":[{"key":"ButtonEventIn","guid":"36FB9BE4BAC1511","pos":{"x":555.1050415039063,"y":917.0745849609375},"links":[{"ipin":"Out","oguid":"50E3DE4C1B5CCBD7","opin":"In"}],"fields":[{"key":"eventName","type":9,"value":"TRY"}]},{"key":"Comment","guid":"6B27A2B1AA0ACDF","pos":{"x":550.7657470703125,"y":876.88623046875},"links":[],"fields":[{"key":"color","type":13,"value":"RGBA(1.000, 1.000, 1.000, 1.000)"},{"key":"comment","type":9,"value":"挑戦する"}]},{"key":"Bind","guid":"99446B40F798FCA","pos":{"x":854.564453125,"y":926.341552734375},"links":[{"ipin":"Out","oguid":"6684C0AD6EF1E532","opin":"In"}],"fields":[{"key":"SerializeData","type":1000,"value":"{\"type\":3,\"target\":\"\",\"values\":[{\"skey\":\"root\",\"dkey\":\"_data\",\"starget\":\"\",\"sfield\":\"\",\"type\":11,\"src\":1,\"dst\":1}]}"}]},{"key":"CheckVideoAdsTryMissionView","guid":"6684C0AD6EF1E532","pos":{"x":997.1234130859375,"y":911.3660888671875},"links":[{"ipin":"True","oguid":"2811BAB7B6BCFC8","opin":"In"}],"fields":[]},{"key":"VideoAdsSetBannerActiveSelection","guid":"2811BAB7B6BCFC8","pos":{"x":1297.427001953125,"y":912.0460205078125},"links":[],"fields":[]},{"key":"ConditionRegion","guid":"50E3DE4C1B5CCBD7","pos":{"x":710.5963134765625,"y":903.905029296875},"links":[{"ipin":"WW","oguid":"99446B40F798FCA","opin":"Bind"}],"fields":[]},{"key":"ButtonEventIn","guid":"1C1BE041DD47326E","pos":{"x":561.4134521484375,"y":1068.4755859375},"links":[{"ipin":"Out","oguid":"A36FEA795973414","opin":"receive"}],"fields":[{"key":"eventName","type":9,"value":"WEB_REDIRECT"}]},{"key":"TargetWebAPI","guid":"A12050EF7EE6B1B","pos":{"x":908.7484741210938,"y":1150.9013671875},"links":[],"fields":[{"key":"Target","type":9,"value":"root"}]},{"key":"Controller","guid":"905FA0B296613C8A","pos":{"x":1099.2646484375,"y":1047.698974609375},"links":[{"ipin":"OutWebRedirect","oguid":"D9599C7A57946C5","opin":"In"},{"ipin":"OutChatRedirect","oguid":"BF4272FD172AF9AB","opin":"In"}],"fields":[]},{"key":"OpenWebView","guid":"D9599C7A57946C5","pos":{"x":1278.805419921875,"y":1077.9703369140625},"links":[],"fields":[{"key":"viewLayer","type":9,"value":"GLOBALMENU"},{"key":"loadMode","type":14,"value":"0"},{"key":"openURL","type":9,"value":""},{"key":"caption","type":9,"value":""},{"key":"openExternal","type":2,"value":"False"},{"key":"bindFromSource","type":2,"value":"True"},{"key":"viewDataType","type":14,"value":"0"}]},{"key":"MissionCheckPeriod","guid":"A36FEA795973414","pos":{"x":721.1358642578125,"y":1054.93994140625},"links":[{"ipin":"True","oguid":"78C145F05F45C3A3","opin":"Open"},{"ipin":"False","oguid":"A12050EF7EE6B1B","opin":"mission/webredirect"}],"fields":[]},{"key":"DialogOneButton","guid":"78C145F05F45C3A3","pos":{"x":879.86572265625,"y":1033.41650390625},"links":[],"fields":[{"key":"button_ok","type":9,"value":""},{"key":"_sys_dialog","type":2,"value":"False"},{"key":"_title","type":9,"value":"Sys.MISSION_TIMEOUT_TRY_TITLE"},{"key":"_msg","type":9,"value":"Sys.MISSION_TIMEOUT_TRY_DESC"},{"key":"_bgTapClose","type":2,"value":"True"},{"key":"_button_ignoreLock","type":2,"value":"True"},{"key":"_auto_release","type":2,"value":"False"}]},{"key":"ButtonEventIn","guid":"AF1A266B71D1C5E","pos":{"x":551.249755859375,"y":1384.640625},"links":[{"ipin":"Out","oguid":"7FFB3C5F559FD889","opin":"receive"}],"fields":[{"key":"eventName","type":9,"value":"CHAT_REDIRECT"}]},{"key":"MissionCheckPeriod","guid":"7FFB3C5F559FD889","pos":{"x":721.95556640625,"y":1383.58642578125},"links":[{"ipin":"True","oguid":"78C145F05F45C3A3","opin":"Open"},{"ipin":"False","oguid":"905FA0B296613C8A","opin":"InChatRedirect"}],"fields":[]},{"key":"PushView","guid":"BF4272FD172AF9AB","pos":{"x":1276.569091796875,"y":1333.7269287109375},"links":[],"fields":[{"key":"viewLayer","type":9,"value":"GLOBALMENU"},{"key":"viewName","type":9,"value":"CHAT_ROOT"},{"key":"loadMode","type":14,"value":"0"},{"key":"isNotOpen","type":2,"value":"False"}]},{"key":"ViewEventIn","guid":"5087EA760F65FBD","pos":{"x":908.3744506835938,"y":1525.643798828125},"links":[{"ipin":"Out","oguid":"905FA0B296613C8A","opin":"updateProg"}],"fields":[{"key":"eventName","type":9,"value":"CHAT_REDIRECT_SUCCESS"}]}]}]}