{"version":"TaskSource_v1.0.0","name":"unit_profilevertical","groups":[{"name":"default","list":[{"key":"ButtonEventIn","guid":"EC54FA4039C46A83","pos":{"x":4.0,"y":82.5},"links":[{"ipin":"Out","oguid":"83126DED5B61FE7C","opin":"ChgImg"}],"fields":[{"key":"eventName","type":9,"value":"CHANGE_IMAGE"}]},{"key":"Comment","guid":"2361D267614E27C9","pos":{"x":2.0,"y":38.5},"links":[],"fields":[{"key":"color","type":13,"value":"RGBA(1.000, 1.000, 1.000, 1.000)"},{"key":"comment","type":9,"value":"2D ・3Dイメージ切り替え"}]},{"key":"ButtonEventIn","guid":"C8489D6D42BA39D","pos":{"x":6.0,"y":213.5},"links":[{"ipin":"Out","oguid":"83126DED5B61FE7C","opin":"InBack"}],"fields":[{"key":"eventName","type":9,"value":"BACK"}]},{"key":"Comment","guid":"9C4EF1CD3146BDC","pos":{"x":5.0,"y":175.5},"links":[],"fields":[{"key":"color","type":13,"value":"RGBA(1.000, 1.000, 1.000, 1.000)"},{"key":"comment","type":9,"value":"戻る"}]},{"key":"RollbackView","guid":"61169D8F47743986","pos":{"x":501.6181640625,"y":212.64547729492188},"links":[],"fields":[{"key":"ControllerType","type":14,"value":"1"},{"key":"Key","type":9,"value":""}]},{"key":"Controller","guid":"83126DED5B61FE7C","pos":{"x":306.9990539550781,"y":56.23712158203125},"links":[{"ipin":"OutBack","oguid":"61169D8F47743986","opin":"In"}],"fields":[]}]}]}