{"infos":[{"key":"TALK_001","value":"Je vous fournirai désormais quelques explications à chaque fois que quelque chose de nouveau apparaîtra."},{"key":"TALK_002","value":"Il ne fait aucun doute que votre avancée dans ce nouveau monde sera pleine de découvertes. Et si nous décollions sans plus tarder ?"},{"key":"DIALOG_001_T","value":"• Quêtes d'histoire •"},{"key":"DIALOG_001_M","value":"• Quêtes d'histoire •<br>Il s'agit de la fonction la plus importante pour progresser dans le jeu. Participer aux quêtes d'histoire vous permettra de <color=#00ffff>débloquer des nombreuses autres fonctions dans le jeu</color>."},{"key":"DIALOG_002_T","value":"• Chapitres, parties et combats •"},{"key":"DIALOG_002_M","value":"Sélectionnez les <color=#00ffff>nouvelles quêtes</color> et terminez-les."},{"key":"SKIP_TITLE","value":"• Quêtes d'histoire •"},{"key":"SKIP_MSG","value":"Voulez-vous lancer le tutoriel sur les quêtes d'histoire ?"},{"key":"SKIP_YES","value":"Oui"},{"key":"SKIP_NO","value":"Non"}]}