{"infos":[{"key":"TALK_001","value":"In „Krieg im Euroshochland“ betreten viele Nationen die Bühne, wie etwa Rundall, Heindler und Ovis."},{"key":"TALK_002","value":"Ich hoffe, du nimmst dir die Zeit zu erfahren, was in jeder der Nationen passiert ist und wie diese zu König Mont stehen."},{"key":"DIALOG_001_T","value":"• Freischaltung des Storyauftrags •"},{"key":"DIALOG_001_M","value":"• Freischaltung des Storyauftrags •<br><color=#00ffff>Storyauftrag — Teil 2</color> wurde freigeschaltet."},{"key":"DIALOG_002_T","value":"• Teil auswählen •"},{"key":"DIALOG_002_M","value":"• Teil auswählen •<br>Du kannst <color=#00ffff>auf dem Auswahlbildschirm zwischen den Teilen wechseln</color>."},{"key":"DIALOG_003_T","value":"• Teile wechseln •"},{"key":"DIALOG_003_M","value":"• Teile wechseln •<br>Selbst wenn du <color=#00ffff>gerade durch Teil 2 spielst</color>, kannst du <color=#00ffff>mit dem vorigen Auftrag weitermachen</color>, indem du <color=#00ffff>auf Teil 1 zurückwechselst</color>."},{"key":"SKIP_TITLE","value":"• Storyaufträge freischalten •"},{"key":"SKIP_MSG","value":"Möchtest du dir die Erklärung zum Freischalten der Storyaufträge anhören?"},{"key":"SKIP_YES","value":"Ja"},{"key":"SKIP_NO","value":"Nein"}]}