{"version":"AISource_v1.0.0","name":"AI_ENEMY_QE_ST_01010110","groups":[{"name":"default","list":[{"key":"Condition","guid":"435DB510AFFF659D","pos":{"x":312.53192138671877,"y":19.9375},"links":[{"ipin":"True","oguid":"C7E4F9B133514A87","opin":"In"},{"ipin":"False","oguid":"C7E4F9B133514A87","opin":"In"}],"fields":[{"key":"CondtionType","type":14,"value":"2"},{"key":"List.value","type":5,"value":"5"}]},{"key":"CommandMove","guid":"A0F5C0DB3BBABC5C","pos":{"x":810.1152954101563,"y":103.66665649414063},"links":[],"fields":[{"key":"Param","type":1000,"value":"{\"flag\":0,\"tflg\":128,\"tid\":\"\",\"tpri\":0,\"tord\":2,\"pos\":{\"x\":0,\"y\":0}}"}]},{"key":"CommandSkill","guid":"C7E4F9B133514A87","pos":{"x":502.71527099609377,"y":22.916656494140626},"links":[{"ipin":"True","oguid":"E7B99E631E543A","opin":"In"},{"ipin":"False","oguid":"6CE1826161BDD59","opin":"In"}],"fields":[{"key":"Param","type":1000,"value":"{\"flag\":1,\"uskill\":\"\",\"ucat\":4,\"uposx\":0,\"uposy\":0,\"tflg\":128,\"tid\":\"\",\"tpri\":0,\"tord\":0,\"spri\":0,\"sord\":18}"}]},{"key":"CommandMove","guid":"5CD5E8CDC69E85A","pos":{"x":330.2147216796875,"y":330.79461669921877},"links":[{"ipin":"True","oguid":"D9B712902A24987","opin":"In"},{"ipin":"False","oguid":"D9B712902A24987","opin":"In"}],"fields":[{"key":"Param","type":1000,"value":"{\"flag\":1,\"tflg\":0,\"tid\":\"\",\"tpri\":0,\"tord\":2,\"pos\":{\"x\":0,\"y\":0}}"}]},{"key":"LocalEventIn","guid":"CA6CEC23262A55EC","pos":{"x":172.19204711914063,"y":338.87127685546877},"links":[{"ipin":"Out","oguid":"5CD5E8CDC69E85A","opin":"In"}],"fields":[{"key":"eventName","type":9,"value":"MOVE_SAFEZONE"}]},{"key":"LocalEventOut","guid":"E7B99E631E543A","pos":{"x":656.0626220703125,"y":22.12664794921875},"links":[],"fields":[{"key":"eventName","type":9,"value":"MOVE_SAFEZONE"}]},{"key":"Comment","guid":"8F20E3F727EB668D","pos":{"x":175.7039794921875,"y":281.29986572265627},"links":[],"fields":[{"key":"color","type":13,"value":"RGBA(1.000, 1.000, 1.000, 1.000)"},{"key":"comment","type":9,"value":"安全な位置へ移動"}]},{"key":"Condition","guid":"C6D55F407642BE10","pos":{"x":194.30899047851563,"y":128.6323699951172},"links":[{"ipin":"False","oguid":"E79EEDD9D861BA","opin":"In"}],"fields":[{"key":"CondtionType","type":14,"value":"32"},{"key":"List.value","type":7,"value":"30"}]},{"key":"LocalEventOut","guid":"E79EEDD9D861BA","pos":{"x":339.07159423828127,"y":164.12168884277345},"links":[],"fields":[{"key":"eventName","type":9,"value":"MOVE_SAFEZONE"}]},{"key":"CommandSkill","guid":"6CE1826161BDD59","pos":{"x":653.7310180664063,"y":130.35711669921876},"links":[{"ipin":"True","oguid":"A0F5C0DB3BBABC5C","opin":"In"},{"ipin":"False","oguid":"A0F5C0DB3BBABC5C","opin":"In"}],"fields":[{"key":"Param","type":1000,"value":"{\"flag\":1,\"uskill\":\"\",\"ucat\":1016,\"uposx\":0,\"uposy\":0,\"tflg\":128,\"tid\":\"\",\"tpri\":0,\"tord\":0,\"spri\":4,\"sord\":159868227}"}]},{"key":"Condition","guid":"D984E21E929AE650","pos":{"x":-75.05673217773438,"y":16.301681518554689},"links":[{"ipin":"True","oguid":"B92E88046D0B3CB","opin":"If"}],"fields":[{"key":"CondtionType","type":14,"value":"2"},{"key":"List.value","type":5,"value":"5"}]},{"key":"SystemEventIn","guid":"899D30C472A868DE","pos":{"x":-255.560302734375,"y":16.449325561523439},"links":[{"ipin":"Out","oguid":"D984E21E929AE650","opin":"If"}],"fields":[{"key":"eventType","type":14,"value":"1"}]},{"key":"Comment","guid":"BB9CCEE9D79623","pos":{"x":646.8587646484375,"y":264.15936279296877},"links":[],"fields":[{"key":"color","type":13,"value":"RGBA(1.000, 1.000, 1.000, 1.000)"},{"key":"comment","type":9,"value":"攻撃しなかったら、回復とか補助行動を行う"}]},{"key":"Condition","guid":"B92E88046D0B3CB","pos":{"x":-50.369476318359378,"y":132.96482849121095},"links":[{"ipin":"False","oguid":"B3B83873E1B0DDAE","opin":"In"},{"ipin":"True","oguid":"435DB510AFFF659D","opin":"If"}],"fields":[{"key":"CondtionType","type":14,"value":"21"},{"key":"List.count","type":5,"value":"3"}]},{"key":"CommandSkill","guid":"B3B83873E1B0DDAE","pos":{"x":-46.824005126953128,"y":253.73739624023438},"links":[{"ipin":"False","oguid":"0E48639CADF2160","opin":"In"}],"fields":[{"key":"Param","type":1000,"value":"{\"flag\":0,\"uskill\":\"\",\"ucat\":4,\"uposx\":0,\"uposy\":0,\"tflg\":384,\"tid\":\"\",\"tpri\":0,\"tord\":15,\"spri\":0,\"sord\":18}"}]},{"key":"CommandSkill","guid":"0E48639CADF2160","pos":{"x":-46.824005126953128,"y":370.7373046875},"links":[],"fields":[{"key":"Param","type":1000,"value":"{\"flag\":0,\"uskill\":\"\",\"ucat\":1016,\"uposx\":0,\"uposy\":0,\"tflg\":64,\"tid\":\"\",\"tpri\":0,\"tord\":0,\"spri\":4,\"sord\":466187587}"}]},{"key":"Comment","guid":"896EE3000FB15","pos":{"x":-48.02532958984375,"y":-41.67976379394531},"links":[],"fields":[{"key":"color","type":13,"value":"RGBA(1.000, 1.000, 1.000, 1.000)"},{"key":"comment","type":9,"value":"2回待機"}]},{"key":"Comment","guid":"DA354B379BF1C","pos":{"x":652.2808837890625,"y":306.7845458984375},"links":[],"fields":[{"key":"color","type":13,"value":"RGBA(1.000, 1.000, 1.000, 1.000)"},{"key":"comment","type":9,"value":"回復スキルHP30%以下"}]},{"key":"Comment","guid":"58DCC79A4BC5899A","pos":{"x":174.83349609375,"y":-149.25390625},"links":[],"fields":[{"key":"color","type":13,"value":"RGBA(1.000, 1.000, 1.000, 1.000)"},{"key":"comment","type":9,"value":"ターゲット優先条件なし"}]},{"key":"Comment","guid":"BCEC66CD1B9F3134","pos":{"x":173.27099609375,"y":-105.50390625},"links":[],"fields":[{"key":"color","type":13,"value":"RGBA(1.000, 1.000, 1.000, 1.000)"},{"key":"comment","type":9,"value":"敵味方のスキル範囲を考慮しない"}]},{"key":"CommandSkill","guid":"D9B712902A24987","pos":{"x":491.4991455078125,"y":334.57421875},"links":[],"fields":[{"key":"Param","type":1000,"value":"{\"flag\":1,\"uskill\":\"\",\"ucat\":4,\"uposx\":0,\"uposy\":0,\"tflg\":128,\"tid\":\"\",\"tpri\":0,\"tord\":0,\"spri\":0,\"sord\":18}"}]}]}],"param":{"flag":0,"hate_border":-100,"mp_border":0,"ap_border":0,"hit_border":0,"buff_border":0,"cond_border":0}}